warawara/__init__.py
warawara/__main__.py
warawara/bin_ntfy.py
warawara/bin_palette.py
warawara/bin_rainbow.py
warawara/bin_sponge.py
warawara/bin_wara.py
warawara/internal_utils.py
warawara/lib_colors.py
warawara/lib_fs.py
warawara/lib_itertools.py
warawara/lib_math.py
warawara/lib_regex.py
warawara/lib_sh.py
warawara/lib_subproc.py
warawara/lib_test_utils.py
warawara/lib_tui.py
warawara/test_bin_wara.py
warawara/test_colors.py
warawara/test_fs.py
warawara/test_internal_utils.py
warawara/test_itertools.py
warawara/test_math.py
warawara/test_regex.py
warawara/test_sh.py
warawara/test_subproc.py
warawara/test_test_utils.py
warawara/test_tui.py
warawara/bin/__init__.py
warawara-0.2.1.dist-info/METADATA
warawara-0.2.1.dist-info/WHEEL
warawara-0.2.1.dist-info/entry_points.txt
warawara-0.2.1.dist-info/licenses/LICENSE
warawara-0.2.1.dist-info/RECORD
